antlerinator/__init__.py
antlerinator/__main__.py
antlerinator/arg.py
antlerinator/build_antlr.py
antlerinator/download.py
antlerinator-1!3.0.1.dist-info/licenses/LICENSE.rst
antlerinator-1!3.0.1.dist-info/METADATA
antlerinator-1!3.0.1.dist-info/WHEEL
antlerinator-1!3.0.1.dist-info/entry_points.txt
antlerinator-1!3.0.1.dist-info/top_level.txt
antlerinator-1!3.0.1.dist-info/RECORD
