Metadata-Version: 2.4
Name: antlerinator
Version: 1!3.0.1
Summary: ANTLeRinator
Home-page: https://github.com/renatahodovan/antlerinator
Author: Renata Hodovan, Akos Kiss
Author-email: hodovan@inf.u-szeged.hu, akiss@inf.u-szeged.hu
License-Expression: BSD-3-Clause
Platform: any
Classifier: Intended Audience :: Developers
Classifier: Operating System :: OS Independent
Classifier: Programming Language :: Python
Classifier: Programming Language :: Python :: 3
Classifier: Programming Language :: Python :: 3.9
Classifier: Programming Language :: Python :: 3.10
Classifier: Programming Language :: Python :: 3.11
Classifier: Programming Language :: Python :: 3.12
Classifier: Programming Language :: Python :: 3.13
Classifier: Topic :: Software Development :: Code Generators
Requires-Python: >=3.9
License-File: LICENSE.rst
Requires-Dist: inators
Requires-Dist: setuptools
Requires-Dist: wheel
Dynamic: license-file
Dynamic: license-expression
